nekofun/__init__.py
nekofun/client.py
nekofun/error.py
nekofun/http.py
nekofun/model.py
nekofun/sync.py
nekofun/utils.py
nekofun-1.0.0.dist-info/METADATA
nekofun-1.0.0.dist-info/WHEEL
nekofun-1.0.0.dist-info/top_level.txt
nekofun-1.0.0.dist-info/RECORD
