Metadata-Version: 2.1
Name: nekofun
Version: 1.0.0
Summary: 일러스트(SFW, NSFW) 크롤링 라이브러리
Home-page: https://github.com/VoidAsMad/nekofun
Author: VoidAsMad
Author-email: voidasmad@gmail.com
License: MIT
Platform: UNKNOWN
Requires-Python: >=3.6
